setup.py
tests/__init__.py
tests/test_addon.py
tests/test_release.py
xam/__init__.py
xam/addon.py
xam/common.py
xam/extensions.py
xam/main.py
xam/main_old.py
xam/repos.py
xam/repository.py
xam.egg-info/PKG-INFO
xam.egg-info/SOURCES.txt
xam.egg-info/dependency_links.txt
xam.egg-info/entry_points.txt
xam.egg-info/requires.txt
xam.egg-info/top_level.txt
xam/cli/__init__.py
xam/cli/release.py